nim_install/__init__.py
nim_install-0.6.0.dist-info/LICENSE
nim_install-0.6.0.dist-info/METADATA
nim_install-0.6.0.dist-info/WHEEL
nim_install-0.6.0.dist-info/entry_points.txt
nim_install-0.6.0.dist-info/namespace_packages.txt
nim_install-0.6.0.dist-info/top_level.txt
nim_install-0.6.0.dist-info/RECORD
