Metadata-Version: 2.1
Name: nim-install
Version: 0.6.0
Summary: install nim compiler in Linux virtualenv assumes gcc
Home-page: https://sourceforge.net/p/nim-install/code/ci/default/tree
Author: Anthon van der Neut
Author-email: a.van.der.neut@ruamel.eu
License: MIT
Platform: UNKNOWN
Classifier: Development Status :: 4 - Beta
Classifier: Intended Audience :: Developers
Classifier: License :: OSI Approved :: MIT License
Classifier: Operating System :: OS Independent
Classifier: Programming Language :: Python
Requires-Dist: backports.lzma ; python_version<="3.3"
